pram.py
pram-0.2.0.dist-info/LICENSE
pram-0.2.0.dist-info/METADATA
pram-0.2.0.dist-info/WHEEL
pram-0.2.0.dist-info/entry_points.txt
pram-0.2.0.dist-info/top_level.txt
pram-0.2.0.dist-info/RECORD
