Metadata-Version: 2.1
Name: pram
Version: 0.2.0
Summary: Python library for implementing post-randomisation method (PRAM) for disclosure control in synthetic data
Home-page: https://github.com/JiscDACT/pram
Download-URL: https://github.com/JiscDACT/pram/tarball/0.2.0
Author: Scott Wilson
Author-email: scott.bradley.wilson@gmail.com
License: MIT
Classifier: Development Status :: 4 - Beta
Classifier: License :: OSI Approved :: MIT License
Classifier: Topic :: Scientific/Engineering :: Mathematics
Classifier: Topic :: Software Development :: Libraries :: Python Modules
Classifier: Programming Language :: Python :: 3.9
Classifier: Programming Language :: Python :: 3.10
Classifier: Programming Language :: Python :: 3.11
License-File: LICENSE
Requires-Dist: pandas
Requires-Dist: numpy
